velbot/__init__.py
velbot/core.py
velbot/bin/__init__.py
velbot/bin/run_velbot.py
velbot/engine/__init__.py
velbot/engine/slackengine.py
velbot/plugins/__init__.py
velbot/plugins/grafanaplugin.py
velbot/plugins/graylogplugin.py
velbot/plugins/jenkinsplugin.py
velbot/plugins/jiraplugin.py
velbot/plugins/repeatplugin.py
velbot/plugins/rundeckplugin.py
velbot/plugins/stashplugin.py
velbot/plugins/velbotcoreplugin.py
velbot/plugins/velbotutilsplugin.py
velbot/utils/__init__.py
velbot/utils/module_loading.py
velbot-1.0.dist-info/DESCRIPTION.rst
velbot-1.0.dist-info/METADATA
velbot-1.0.dist-info/RECORD
velbot-1.0.dist-info/WHEEL
velbot-1.0.dist-info/entry_points.txt
velbot-1.0.dist-info/metadata.json
velbot-1.0.dist-info/top_level.txt
