Metadata-Version: 2.0
Name: velbot
Version: 1.0
Summary: A HTTP Based Slack Bot Written in Python.
Home-page: https://github.com/sanjimenon/python-velbot
Author: Sanjit Menon
Author-email: sanjimenon@yahoo.com
License: UNKNOWN
Platform: UNKNOWN
Requires-Dist: Flask
Requires-Dist: pyyaml (>=3,<4)
Requires-Dist: slackclient (>=1,<2)
